{
  "contacts": [
    {
      "name": "Milo Campbell",
      "emailAddress": "medhurst.london@gmail.com",
      "phoneNumber": "+1-980-810-8129",
      "communicationAddress": "68910 Cassin Springs Apt. 654 Rogelioshire, WI 24270",
      "walletAddress": "1Mgwnf3J9993cYw3nYFnuC6jLdEfU62axC"
    },
    {
      "name": "Brantley Sanders",
      "emailAddress": "alec13@gmail.com",
      "phoneNumber": "+1-867-231-8082",
      "communicationAddress": "77452 Brigitte Stravenue Suite 011 North Gussie, HI 85749-6043",
      "walletAddress": "17tDyRQS4BBBLijuQzt3a7PkjXWLsWNtfM"
    },
    {
      "name": "Wyatt Reyes",
      "emailAddress": "collier.lenore@borer.org",
      "phoneNumber": "+1-568-928-5743",
      "communicationAddress": "955 Willis Trail Apt. 698 Ismaelmouth, ID 22781-4695",
      "walletAddress": "1VbvwH5AnuhngpVnE9jUicVoXDukBefKB"
    },
    {
      "name": "Erick Brooks",
      "emailAddress": "fernando45@hotmail.com",
      "phoneNumber": "(309) 317-7124",
      "communicationAddress": "267 Gordon Vista Suite 038 New Nigel, IA 00171",
      "walletAddress": "1AbWNbzGaj1h8kDMxqssXZcx5dLUMUvAE3"
    },
    {
      "name": "Jacob Reed",
      "emailAddress": "darryl95@langosh.com",
      "phoneNumber": "(269) 855-5797",
      "communicationAddress": "429 Adriana Gateway Suite 030 West Rhoda, IA 41230",
      "walletAddress": "1Cqxoeappm7d5osTYJzw7exqePXijCfxbC"
    },
    {
      "name": "Josue Davidson",
      "emailAddress": "astrid.okon@oreilly.info",
      "phoneNumber": "+1-872-750-8133",
      "communicationAddress": "4714 Dion Locks Apt. 930 West Jakayla, MN 34990-7785",
      "walletAddress": "1KTGazRPSGurcdeJq3JsrxjYhxMXzCA3Rf"
    },
    {
      "name": "Sawyer Harrison",
      "emailAddress": "roslyn.beer@bogan.com",
      "phoneNumber": "486-248-4885",
      "communicationAddress": "6516 Thiel Parkway Suite 173 Lesterberg, WY 10941-8787",
      "walletAddress": "1DyqpwpCjZTwh5UStGPcVHEQKxnZXTKMRB"
    },
    {
      "name": "Zion Fleming",
      "emailAddress": "west.bertram@yahoo.com",
      "phoneNumber": "979-741-7453",
      "communicationAddress": "8415 Reece Path East Domenicofurt, MO 42653",
      "walletAddress": "1CEyDPVLhmJwehEb1jxcvLtNCJNNJGATBy"
    },
    {
      "name": "Jayden Stokes",
      "emailAddress": "wyman.amanda@gmail.com",
      "phoneNumber": "+16237872255",
      "communicationAddress": "407 Vandervort Trail North Dustinville, AL 48663-5843",
      "walletAddress": "19c3rmRdcsPqCizpC55qTkQZc1ESbyVwaf"
    },
    {
      "name": "Emily May",
      "emailAddress": "greenfelder.maybell@stanton.org",
      "phoneNumber": "(760) 260-7252",
      "communicationAddress": "5510 Bosco Circle Jaststad, RI 80672-3371",
      "walletAddress": "17hSnMkhTD5bwLwGch7jmkcER384xNDFix"
    },
    {
      "name": "Martin Carter",
      "emailAddress": "lockman.brielle@yahoo.com",
      "phoneNumber": "853-963-6752",
      "communicationAddress": "336 Angelina Burgs Apt. 564 Port Timothy, AL 77987",
      "walletAddress": "1Mz89bt1AK6aE46GYN1voxvYJ9kKJn45Cz"
    },
    {
      "name": "Josephine Cruz",
      "emailAddress": "kwaelchi@bins.com",
      "phoneNumber": "626-960-6787",
      "communicationAddress": "224 Lenny Rest Apt. 018 Jovanberg, WV 54952-9759",
      "walletAddress": "1Ak7A9gTnpFmpcMSRa7vAX3y2STBAfWYoE"
    },
    {
      "name": "Christopher Lee",
      "emailAddress": "cordell87@yahoo.com",
      "phoneNumber": "+1-629-765-0039",
      "communicationAddress": "639 Gusikowski Road Apt. 514 Kertzmannbury, ID 67871",
      "walletAddress": "14jfMHazcZkzPrfuPfbEzaWTpoB1Du6KGY"
    },
    {
      "name": "Liam Webster",
      "emailAddress": "elton75@mills.com",
      "phoneNumber": "+1-219-727-4267",
      "communicationAddress": "9789 Zoie Bridge Suite 529 Durganborough, WV 96977",
      "walletAddress": "1DZpQZDbjU3ynt24pHYRCoRuaJLXjRgL3Q"
    },
    {
      "name": "Kinsley Thompson",
      "emailAddress": "morar.jannie@hane.org",
      "phoneNumber": "+1-392-703-9254",
      "communicationAddress": "21205 Stracke Mountains Krajcikmouth, WY 09798",
      "walletAddress": "1LLzniW5EnfJy9NtaoJAEK1W25BJ24NTDL"
    }
  ]
}
